fm_actor/__init__.py
fm_actor/benchexec_helper.py
fm_actor/download.py
fm_actor/exceptions.py
fm_actor/files.py
fm_actor/fmdata.py
fm_actor/run.py
fm_actor/types.py
fm_actor/zenodo.py
fm_actor-0.2.0.dist-info/METADATA
fm_actor-0.2.0.dist-info/WHEEL
fm_actor-0.2.0.dist-info/RECORD
