Metadata-Version: 2.3
Name: fm-actor
Version: 0.2.0
Author-email: Henrik Wachowitz <henrik.wachowitz@ifi.lmu.de>
Maintainer-email: Henrik Wachowitz <henrik.wachowitz@ifi.lmu.de>
Classifier: Development Status :: 4 - Beta
Classifier: Intended Audience :: Developers
Classifier: License :: OSI Approved :: MIT License
Classifier: Programming Language :: Python :: 3.10
Classifier: Programming Language :: Python :: 3.11
Requires-Python: >=3.10
Requires-Dist: benchexec>=3.21
Requires-Dist: httpx>=0.26
Requires-Dist: pyyaml>=6.0
Requires-Dist: tomli>=2.0; python_version <= '3.10'
Requires-Dist: tqdm>=4.66
Requires-Dist: werkzeug>=3.0
